libname/ReproCipher.py
libname/Substitution_Ciphers.py
libname/__init__.py
reprocipher-0.0.2.dist-info/LICENSE
reprocipher-0.0.2.dist-info/METADATA
reprocipher-0.0.2.dist-info/WHEEL
reprocipher-0.0.2.dist-info/top_level.txt
reprocipher-0.0.2.dist-info/RECORD
